{"location": "./results/exp3/SetTransformer/exp3_2026-03-04_14-09-11_MALLOWS-RELPHI", "architecture": "SetTransformer", "max_num_voters": 55, "max_num_alternatives": 5, "election_sampling": {"probmodel": "MALLOWS-RELPHI"}, "num_gradient_steps": 15000, "report_intervals": 2500, "eval_dataset_size": 500, "model_to_rule": {"plain": true, "neut-averaged": null, "neut-anon-averaged": false}, "sample_size_applicable": 400, "sample_size_maximal": 10000, "architecture_parameters": {"d_model": 128, "n_heads": 4, "d_head": 32, "n_encoder_layers": 4, "pma_outputs": 1}, "axioms_check_model_interim": ["Anonymity", "Neutrality", "Condorcet", "Pareto", "Independence"], "axioms_check_rule": ["Condorcet", "Independence"], "axiom_opt": {"No_winner": {"weight": 10, "period": "always"}, "All_winners": null, "Inadmissible": null, "Resoluteness": null, "Parity": null, "Anonymity": null, "Neutrality": null, "Condorcet1": {"weight": 1, "period": "always"}, "Condorcet2": null, "Pareto1": {"weight": 1, "period": "always"}, "Pareto2": null, "Independence": null}, "comp_rules_axioms": ["Stable Voting", "Blacks", "Borda", "Weak Nanson", "Copeland", "Baldwin", "Kemeny-Young"], "comp_rules_similarity": ["Stable Voting", "Blacks", "Borda", "Weak Nanson", "Copeland"], "distance": "L2", "random_seed": 42, "batch_size": 200, "learning_rate": 0.001, "learning_scheduler": 1000, "weight_decay": 0, "loss_report_intervals": 500, "save_model": true, "load_model_from": null, "loss curve": {"0": {"loss_nowi": 0.09835213422775269, "loss_alwi": 0, "loss_inad": 0, "loss_reso": 0, "loss_pari": 0, "loss_anon": 0, "loss_neut": 0, "loss_con1": 0.8558871150016785, "loss_con2": 0, "loss_par1": 0.20936360955238342, "loss_par2": 0, "loss_inde": 0}, "500": {"loss_nowi": 0.0, "loss_alwi": 0, "loss_inad": 0, "loss_reso": 0, "loss_pari": 0, "loss_anon": 0, "loss_neut": 0, "loss_con1": 0.11691571027040482, "loss_con2": 0, "loss_par1": 0.1401088684797287, "loss_par2": 0, "loss_inde": 0}, "1000": {"loss_nowi": 0.0, "loss_alwi": 0, "loss_inad": 0, "loss_reso": 0, "loss_pari": 0, "loss_anon": 0, "loss_neut": 0, "loss_con1": 0.056223396211862564, "loss_con2": 0, "loss_par1": 0.1103772222995758, "loss_par2": 0, "loss_inde": 0}, "1500": {"loss_nowi": 0.0, "loss_alwi": 0, "loss_inad": 0, "loss_reso": 0, "loss_pari": 0, "loss_anon": 0, "loss_neut": 0, "loss_con1": 0.07556906342506409, "loss_con2": 0, "loss_par1": 0.06067290157079697, "loss_par2": 0, "loss_inde": 0}, "2000": {"loss_nowi": 0.0, "loss_alwi": 0, "loss_inad": 0, "loss_reso": 0, "loss_pari": 0, "loss_anon": 0, "loss_neut": 0, "loss_con1": 0.04613354429602623, "loss_con2": 0, "loss_par1": 0.04296792298555374, "loss_par2": 0, "loss_inde": 0}, "2500": {"loss_nowi": 0.0, "loss_alwi": 0, "loss_inad": 0, "loss_reso": 0, "loss_pari": 0, "loss_anon": 0, "loss_neut": 0, "loss_con1": 0.1129029244184494, "loss_con2": 0, "loss_par1": 0.04446004331111908, "loss_par2": 0, "loss_inde": 0}, "3000": {"loss_nowi": 0.0, "loss_alwi": 0, "loss_inad": 0, "loss_reso": 0, "loss_pari": 0, "loss_anon": 0, "loss_neut": 0, "loss_con1": 0.04460641369223595, "loss_con2": 0, "loss_par1": 0.059654902666807175, "loss_par2": 0, "loss_inde": 0}, "3500": {"loss_nowi": 0.0, "loss_alwi": 0, "loss_inad": 0, "loss_reso": 0, "loss_pari": 0, "loss_anon": 0, "loss_neut": 0, "loss_con1": 0.07725869864225388, "loss_con2": 0, "loss_par1": 0.044180501252412796, "loss_par2": 0, "loss_inde": 0}, "4000": {"loss_nowi": 0.0, "loss_alwi": 0, "loss_inad": 0, "loss_reso": 0, "loss_pari": 0, "loss_anon": 0, "loss_neut": 0, "loss_con1": 0.04340381175279617, "loss_con2": 0, "loss_par1": 0.051786329597234726, "loss_par2": 0, "loss_inde": 0}, "4500": {"loss_nowi": 0.0, "loss_alwi": 0, "loss_inad": 0, "loss_reso": 0, "loss_pari": 0, "loss_anon": 0, "loss_neut": 0, "loss_con1": 0.05376081168651581, "loss_con2": 0, "loss_par1": 0.08803382515907288, "loss_par2": 0, "loss_inde": 0}, "5000": {"loss_nowi": 0.0, "loss_alwi": 0, "loss_inad": 0, "loss_reso": 0, "loss_pari": 0, "loss_anon": 0, "loss_neut": 0, "loss_con1": 0.044837649911642075, "loss_con2": 0, "loss_par1": 0.06686198711395264, "loss_par2": 0, "loss_inde": 0}, "5500": {"loss_nowi": 0.0, "loss_alwi": 0, "loss_inad": 0, "loss_reso": 0, "loss_pari": 0, "loss_anon": 0, "loss_neut": 0, "loss_con1": 0.06864737719297409, "loss_con2": 0, "loss_par1": 0.07472830265760422, "loss_par2": 0, "loss_inde": 0}, "6000": {"loss_nowi": 0.0, "loss_alwi": 0, "loss_inad": 0, "loss_reso": 0, "loss_pari": 0, "loss_anon": 0, "loss_neut": 0, "loss_con1": 0.022617356851696968, "loss_con2": 0, "loss_par1": 0.044957101345062256, "loss_par2": 0, "loss_inde": 0}, "6500": {"loss_nowi": 0.0, "loss_alwi": 0, "loss_inad": 0, "loss_reso": 0, "loss_pari": 0, "loss_anon": 0, "loss_neut": 0, "loss_con1": 0.09485900402069092, "loss_con2": 0, "loss_par1": 0.0918949693441391, "loss_par2": 0, "loss_inde": 0}, "7000": {"loss_nowi": 0.0, "loss_alwi": 0, "loss_inad": 0, "loss_reso": 0, "loss_pari": 0, "loss_anon": 0, "loss_neut": 0, "loss_con1": 0.0354459173977375, "loss_con2": 0, "loss_par1": 0.03346455842256546, "loss_par2": 0, "loss_inde": 0}, "7500": {"loss_nowi": 0.0, "loss_alwi": 0, "loss_inad": 0, "loss_reso": 0, "loss_pari": 0, "loss_anon": 0, "loss_neut": 0, "loss_con1": 0.09017418324947357, "loss_con2": 0, "loss_par1": 0.043165359646081924, "loss_par2": 0, "loss_inde": 0}, "8000": {"loss_nowi": 0.0, "loss_alwi": 0, "loss_inad": 0, "loss_reso": 0, "loss_pari": 0, "loss_anon": 0, "loss_neut": 0, "loss_con1": 0.04635866358876228, "loss_con2": 0, "loss_par1": 0.05275929719209671, "loss_par2": 0, "loss_inde": 0}, "8500": {"loss_nowi": 0.0, "loss_alwi": 0, "loss_inad": 0, "loss_reso": 0, "loss_pari": 0, "loss_anon": 0, "loss_neut": 0, "loss_con1": 0.16815465688705444, "loss_con2": 0, "loss_par1": 0.052513688802719116, "loss_par2": 0, "loss_inde": 0}, "9000": {"loss_nowi": 0.0, "loss_alwi": 0, "loss_inad": 0, "loss_reso": 0, "loss_pari": 0, "loss_anon": 0, "loss_neut": 0, "loss_con1": 0.022033343091607094, "loss_con2": 0, "loss_par1": 0.03458835929632187, "loss_par2": 0, "loss_inde": 0}, "9500": {"loss_nowi": 0.0, "loss_alwi": 0, "loss_inad": 0, "loss_reso": 0, "loss_pari": 0, "loss_anon": 0, "loss_neut": 0, "loss_con1": 0.04105252027511597, "loss_con2": 0, "loss_par1": 0.04710250720381737, "loss_par2": 0, "loss_inde": 0}, "10000": {"loss_nowi": 0.0, "loss_alwi": 0, "loss_inad": 0, "loss_reso": 0, "loss_pari": 0, "loss_anon": 0, "loss_neut": 0, "loss_con1": 0.04008369520306587, "loss_con2": 0, "loss_par1": 0.10903200507164001, "loss_par2": 0, "loss_inde": 0}, "10500": {"loss_nowi": 0.0, "loss_alwi": 0, "loss_inad": 0, "loss_reso": 0, "loss_pari": 0, "loss_anon": 0, "loss_neut": 0, "loss_con1": 0.060580261051654816, "loss_con2": 0, "loss_par1": 0.07759080082178116, "loss_par2": 0, "loss_inde": 0}, "11000": {"loss_nowi": 0.0, "loss_alwi": 0, "loss_inad": 0, "loss_reso": 0, "loss_pari": 0, "loss_anon": 0, "loss_neut": 0, "loss_con1": 0.030645539984107018, "loss_con2": 0, "loss_par1": 0.0481465719640255, "loss_par2": 0, "loss_inde": 0}, "11500": {"loss_nowi": 0.0, "loss_alwi": 0, "loss_inad": 0, "loss_reso": 0, "loss_pari": 0, "loss_anon": 0, "loss_neut": 0, "loss_con1": 0.03165232017636299, "loss_con2": 0, "loss_par1": 0.055264897644519806, "loss_par2": 0, "loss_inde": 0}, "12000": {"loss_nowi": 0.0, "loss_alwi": 0, "loss_inad": 0, "loss_reso": 0, "loss_pari": 0, "loss_anon": 0, "loss_neut": 0, "loss_con1": 0.053084343671798706, "loss_con2": 0, "loss_par1": 0.07867240905761719, "loss_par2": 0, "loss_inde": 0}, "12500": {"loss_nowi": 0.0, "loss_alwi": 0, "loss_inad": 0, "loss_reso": 0, "loss_pari": 0, "loss_anon": 0, "loss_neut": 0, "loss_con1": 0.03545910120010376, "loss_con2": 0, "loss_par1": 0.05662025883793831, "loss_par2": 0, "loss_inde": 0}, "13000": {"loss_nowi": 0.0, "loss_alwi": 0, "loss_inad": 0, "loss_reso": 0, "loss_pari": 0, "loss_anon": 0, "loss_neut": 0, "loss_con1": 0.03004833124577999, "loss_con2": 0, "loss_par1": 0.0854305624961853, "loss_par2": 0, "loss_inde": 0}, "13500": {"loss_nowi": 0.0, "loss_alwi": 0, "loss_inad": 0, "loss_reso": 0, "loss_pari": 0, "loss_anon": 0, "loss_neut": 0, "loss_con1": 0.037309013307094574, "loss_con2": 0, "loss_par1": 0.04866981506347656, "loss_par2": 0, "loss_inde": 0}, "14000": {"loss_nowi": 0.0, "loss_alwi": 0, "loss_inad": 0, "loss_reso": 0, "loss_pari": 0, "loss_anon": 0, "loss_neut": 0, "loss_con1": 0.043960027396678925, "loss_con2": 0, "loss_par1": 0.0650504007935524, "loss_par2": 0, "loss_inde": 0}, "14500": {"loss_nowi": 0.0, "loss_alwi": 0, "loss_inad": 0, "loss_reso": 0, "loss_pari": 0, "loss_anon": 0, "loss_neut": 0, "loss_con1": 0.03964252024888992, "loss_con2": 0, "loss_par1": 0.03853045031428337, "loss_par2": 0, "loss_inde": 0}}, "learning curve": {"2499": {"loss_on_last_batch": {"loss_nowi": 0.0, "loss_alwi": 0, "loss_inad": 0, "loss_reso": 0, "loss_pari": 0, "loss_anon": 0, "loss_neut": 0, "loss_con1": 0.10996893793344498, "loss_con2": 0, "loss_par1": 0.10019481182098389, "loss_par2": 0, "loss_inde": 0}, "admissability": {"plain": {"no_winner_at_all": 0.0, "no_admissible_winner": 0.0, "all_admissible_winner": 0.242, "some_inadmissible_winner": 0.746}, "neut": {"no_winner_at_all": 0.0, "no_admissible_winner": 0.0, "all_admissible_winner": 0.306, "some_inadmissible_winner": 0.764}, "neut-anon": null}, "axiom_satisfaction": {"plain": {"Anonymity": {"sampling_as_desired": "Yes (400/400)", "cond_satisfaction": 1.0, "absolute_satisfaction": 1.0, "percent_applicable": 1.0}, "Neutrality": {"sampling_as_desired": "Yes (400/400)", "cond_satisfaction": 0.37, "absolute_satisfaction": 0.37, "percent_applicable": 1.0}, "Condorcet": {"sampling_as_desired": "Yes (400/400)", "cond_satisfaction": 0.7075, "absolute_satisfaction": 0.7723735408560312, "percent_applicable": 0.7782101167315175}, "Pareto": {"sampling_as_desired": "Yes (400/400)", "cond_satisfaction": 0.9875, "absolute_satisfaction": 0.9993540886190415, "percent_applicable": 0.0516729104766826}, "Independence": {"sampling_as_desired": "Yes (400/400)", "cond_satisfaction": 0.2675, "absolute_satisfaction": 0.44507575757575757, "percent_applicable": 0.7575757575757576}}, "neut": {"Anonymity": {"sampling_as_desired": "Yes (400/400)", "cond_satisfaction": 1.0, "absolute_satisfaction": 1.0, "percent_applicable": 1.0}, "Neutrality": {"sampling_as_desired": "Yes (400/400)", "cond_satisfaction": 1.0, "absolute_satisfaction": 1.0, "percent_applicable": 1.0}, "Condorcet": {"sampling_as_desired": "Yes (400/400)", "cond_satisfaction": 0.7475, "absolute_satisfaction": 0.7947154471544715, "percent_applicable": 0.8130081300813008}, "Pareto": {"sampling_as_desired": "Yes (400/400)", "cond_satisfaction": 1.0, "absolute_satisfaction": 1.0, "percent_applicable": 0.04803073967339097}, "Independence": {"sampling_as_desired": "Yes (400/400)", "cond_satisfaction": 0.2425, "absolute_satisfaction": 0.45207956600361665, "percent_applicable": 0.7233273056057866}}, "neut-anon": null}, "similarity_to_other_rules": {"plain": {"Stable Voting": {"hamming": 0.1681666666666667, "identity_accu": 0.592, "overlap_accu": 0.984, "subset_accu": 0.618, "superset_accu": 0.954}, "Blacks": {"hamming": 0.17209999999999998, "identity_accu": 0.59, "overlap_accu": 0.982, "subset_accu": 0.614, "superset_accu": 0.946}, "Borda": {"hamming": 0.17339999999999997, "identity_accu": 0.584, "overlap_accu": 0.982, "subset_accu": 0.612, "superset_accu": 0.94}, "Weak Nanson": {"hamming": 0.16929999999999998, "identity_accu": 0.588, "overlap_accu": 0.986, "subset_accu": 0.624, "superset_accu": 0.932}, "Copeland": {"hamming": 0.1652, "identity_accu": 0.594, "overlap_accu": 0.988, "subset_accu": 0.642, "superset_accu": 0.912}}, "neut": {"Stable Voting": {"hamming": 0.13210000000000005, "identity_accu": 0.674, "overlap_accu": 1.0, "subset_accu": 0.674, "superset_accu": 1.0}, "Blacks": {"hamming": 0.1324333333333334, "identity_accu": 0.672, "overlap_accu": 1.0, "subset_accu": 0.672, "superset_accu": 1.0}, "Borda": {"hamming": 0.12986666666666674, "identity_accu": 0.682, "overlap_accu": 1.0, "subset_accu": 0.682, "superset_accu": 1.0}, "Weak Nanson": {"hamming": 0.12236666666666673, "identity_accu": 0.704, "overlap_accu": 1.0, "subset_accu": 0.706, "superset_accu": 0.998}, "Copeland": {"hamming": 0.11220000000000009, "identity_accu": 0.708, "overlap_accu": 1.0, "subset_accu": 0.722, "superset_accu": 0.986}}, "neut-anon": null}}, "4999": {"loss_on_last_batch": {"loss_nowi": 0.0, "loss_alwi": 0, "loss_inad": 0, "loss_reso": 0, "loss_pari": 0, "loss_anon": 0, "loss_neut": 0, "loss_con1": 0.019132152199745178, "loss_con2": 0, "loss_par1": 0.04207868129014969, "loss_par2": 0, "loss_inde": 0}, "admissability": {"plain": {"no_winner_at_all": 0.0, "no_admissible_winner": 0.0, "all_admissible_winner": 0.402, "some_inadmissible_winner": 0.61}, "neut": {"no_winner_at_all": 0.0, "no_admissible_winner": 0.0, "all_admissible_winner": 0.49, "some_inadmissible_winner": 0.632}, "neut-anon": null}, "axiom_satisfaction": {"plain": {"Anonymity": {"sampling_as_desired": "Yes (400/400)", "cond_satisfaction": 1.0, "absolute_satisfaction": 1.0, "percent_applicable": 1.0}, "Neutrality": {"sampling_as_desired": "Yes (400/400)", "cond_satisfaction": 0.2925, "absolute_satisfaction": 0.2925, "percent_applicable": 1.0}, "Condorcet": {"sampling_as_desired": "Yes (400/400)", "cond_satisfaction": 0.435, "absolute_satisfaction": 0.5330578512396694, "percent_applicable": 0.8264462809917356}, "Pareto": {"sampling_as_desired": "Yes (400/400)", "cond_satisfaction": 0.94, "absolute_satisfaction": 0.9973085118313334, "percent_applicable": 0.0448581361444432}, "Independence": {"sampling_as_desired": "Yes (400/400)", "cond_satisfaction": 0.16, "absolute_satisfaction": 0.5130434782608696, "percent_applicable": 0.5797101449275363}}, "neut": {"Anonymity": {"sampling_as_desired": "Yes (400/400)", "cond_satisfaction": 1.0, "absolute_satisfaction": 1.0, "percent_applicable": 1.0}, "Neutrality": {"sampling_as_desired": "Yes (400/400)", "cond_satisfaction": 1.0, "absolute_satisfaction": 1.0, "percent_applicable": 1.0}, "Condorcet": {"sampling_as_desired": "Yes (400/400)", "cond_satisfaction": 0.465, "absolute_satisfaction": 0.5745526838966203, "percent_applicable": 0.7952286282306164}, "Pareto": {"sampling_as_desired": "Yes (400/400)", "cond_satisfaction": 0.9975, "absolute_satisfaction": 0.9998824635637047, "percent_applicable": 0.047014574518100614}, "Independence": {"sampling_as_desired": "Yes (400/400)", "cond_satisfaction": 0.1575, "absolute_satisfaction": 0.5905224787363305, "percent_applicable": 0.48602673147023084}}, "neut-anon": null}, "similarity_to_other_rules": {"plain": {"Stable Voting": {"hamming": 0.2666333333333333, "identity_accu": 0.4, "overlap_accu": 0.996, "subset_accu": 0.408, "superset_accu": 0.984}, "Blacks": {"hamming": 0.27010000000000006, "identity_accu": 0.4, "overlap_accu": 0.992, "subset_accu": 0.408, "superset_accu": 0.978}, "Borda": {"hamming": 0.2688666666666668, "identity_accu": 0.404, "overlap_accu": 0.99, "subset_accu": 0.412, "superset_accu": 0.976}, "Weak Nanson": {"hamming": 0.25850000000000006, "identity_accu": 0.414, "overlap_accu": 0.994, "subset_accu": 0.424, "superset_accu": 0.978}, "Copeland": {"hamming": 0.25660000000000005, "identity_accu": 0.42, "overlap_accu": 1.0, "subset_accu": 0.442, "superset_accu": 0.948}}, "neut": {"Stable Voting": {"hamming": 0.2960333333333331, "identity_accu": 0.366, "overlap_accu": 1.0, "subset_accu": 0.366, "superset_accu": 0.998}, "Blacks": {"hamming": 0.29636666666666645, "identity_accu": 0.37, "overlap_accu": 1.0, "subset_accu": 0.37, "superset_accu": 0.998}, "Borda": {"hamming": 0.29513333333333314, "identity_accu": 0.374, "overlap_accu": 0.998, "subset_accu": 0.374, "superset_accu": 0.996}, "Weak Nanson": {"hamming": 0.28429999999999966, "identity_accu": 0.39, "overlap_accu": 1.0, "subset_accu": 0.39, "superset_accu": 1.0}, "Copeland": {"hamming": 0.26879999999999993, "identity_accu": 0.402, "overlap_accu": 1.0, "subset_accu": 0.406, "superset_accu": 0.994}}, "neut-anon": null}}, "7499": {"loss_on_last_batch": {"loss_nowi": 0.0, "loss_alwi": 0, "loss_inad": 0, "loss_reso": 0, "loss_pari": 0, "loss_anon": 0, "loss_neut": 0, "loss_con1": 0.09944073110818863, "loss_con2": 0, "loss_par1": 0.06713330000638962, "loss_par2": 0, "loss_inde": 0}, "admissability": {"plain": {"no_winner_at_all": 0.0, "no_admissible_winner": 0.0, "all_admissible_winner": 0.348, "some_inadmissible_winner": 0.714}, "neut": {"no_winner_at_all": 0.0, "no_admissible_winner": 0.0, "all_admissible_winner": 0.484, "some_inadmissible_winner": 0.622}, "neut-anon": null}, "axiom_satisfaction": {"plain": {"Anonymity": {"sampling_as_desired": "Yes (400/400)", "cond_satisfaction": 1.0, "absolute_satisfaction": 1.0, "percent_applicable": 1.0}, "Neutrality": {"sampling_as_desired": "Yes (400/400)", "cond_satisfaction": 0.3625, "absolute_satisfaction": 0.3625, "percent_applicable": 1.0}, "Condorcet": {"sampling_as_desired": "Yes (400/400)", "cond_satisfaction": 0.5775, "absolute_satisfaction": 0.6673228346456693, "percent_applicable": 0.7874015748031497}, "Pareto": {"sampling_as_desired": "Yes (400/400)", "cond_satisfaction": 0.95, "absolute_satisfaction": 0.997681428240204, "percent_applicable": 0.04637143519591931}, "Independence": {"sampling_as_desired": "Yes (400/400)", "cond_satisfaction": 0.2575, "absolute_satisfaction": 0.5209677419354839, "percent_applicable": 0.6451612903225806}}, "neut": {"Anonymity": {"sampling_as_desired": "Yes (400/400)", "cond_satisfaction": 1.0, "absolute_satisfaction": 1.0, "percent_applicable": 1.0}, "Neutrality": {"sampling_as_desired": "Yes (400/400)", "cond_satisfaction": 1.0, "absolute_satisfaction": 1.0, "percent_applicable": 1.0}, "Condorcet": {"sampling_as_desired": "Yes (400/400)", "cond_satisfaction": 0.6675, "absolute_satisfaction": 0.7307692307692307, "percent_applicable": 0.8097165991902834}, "Pareto": {"sampling_as_desired": "Yes (400/400)", "cond_satisfaction": 1.0, "absolute_satisfaction": 1.0, "percent_applicable": 0.049554013875123884}, "Independence": {"sampling_as_desired": "Yes (400/400)", "cond_satisfaction": 0.375, "absolute_satisfaction": 0.6778350515463918, "percent_applicable": 0.5154639175257731}}, "neut-anon": null}, "similarity_to_other_rules": {"plain": {"Stable Voting": {"hamming": 0.21959999999999996, "identity_accu": 0.532, "overlap_accu": 0.988, "subset_accu": 0.536, "superset_accu": 0.982}, "Blacks": {"hamming": 0.2191333333333333, "identity_accu": 0.534, "overlap_accu": 0.99, "subset_accu": 0.538, "superset_accu": 0.984}, "Borda": {"hamming": 0.21856666666666663, "identity_accu": 0.532, "overlap_accu": 0.988, "subset_accu": 0.536, "superset_accu": 0.98}, "Weak Nanson": {"hamming": 0.2206, "identity_accu": 0.532, "overlap_accu": 0.984, "subset_accu": 0.542, "superset_accu": 0.958}, "Copeland": {"hamming": 0.20630000000000004, "identity_accu": 0.54, "overlap_accu": 0.992, "subset_accu": 0.558, "superset_accu": 0.956}}, "neut": {"Stable Voting": {"hamming": 0.25396666666666645, "identity_accu": 0.588, "overlap_accu": 1.0, "subset_accu": 0.588, "superset_accu": 1.0}, "Blacks": {"hamming": 0.25429999999999986, "identity_accu": 0.588, "overlap_accu": 1.0, "subset_accu": 0.588, "superset_accu": 1.0}, "Borda": {"hamming": 0.2517333333333332, "identity_accu": 0.594, "overlap_accu": 1.0, "subset_accu": 0.594, "superset_accu": 1.0}, "Weak Nanson": {"hamming": 0.24323333333333316, "identity_accu": 0.608, "overlap_accu": 1.0, "subset_accu": 0.608, "superset_accu": 1.0}, "Copeland": {"hamming": 0.22859999999999986, "identity_accu": 0.622, "overlap_accu": 1.0, "subset_accu": 0.626, "superset_accu": 0.996}}, "neut-anon": null}}, "9999": {"loss_on_last_batch": {"loss_nowi": 0.0, "loss_alwi": 0, "loss_inad": 0, "loss_reso": 0, "loss_pari": 0, "loss_anon": 0, "loss_neut": 0, "loss_con1": 0.025573741644620895, "loss_con2": 0, "loss_par1": 0.0423460528254509, "loss_par2": 0, "loss_inde": 0}, "admissability": {"plain": {"no_winner_at_all": 0.0, "no_admissible_winner": 0.0, "all_admissible_winner": 0.406, "some_inadmissible_winner": 0.59}, "neut": {"no_winner_at_all": 0.0, "no_admissible_winner": 0.0, "all_admissible_winner": 0.456, "some_inadmissible_winner": 0.528}, "neut-anon": null}, "axiom_satisfaction": {"plain": {"Anonymity": {"sampling_as_desired": "Yes (400/400)", "cond_satisfaction": 1.0, "absolute_satisfaction": 1.0, "percent_applicable": 1.0}, "Neutrality": {"sampling_as_desired": "Yes (400/400)", "cond_satisfaction": 0.39, "absolute_satisfaction": 0.39, "percent_applicable": 1.0}, "Condorcet": {"sampling_as_desired": "Yes (400/400)", "cond_satisfaction": 0.45, "absolute_satisfaction": 0.5473251028806584, "percent_applicable": 0.823045267489712}, "Pareto": {"sampling_as_desired": "Yes (400/400)", "cond_satisfaction": 0.9475, "absolute_satisfaction": 0.9972723730354591, "percent_applicable": 0.05195479932458761}, "Independence": {"sampling_as_desired": "Yes (400/400)", "cond_satisfaction": 0.1425, "absolute_satisfaction": 0.5, "percent_applicable": 0.5830903790087464}}, "neut": {"Anonymity": {"sampling_as_desired": "Yes (400/400)", "cond_satisfaction": 1.0, "absolute_satisfaction": 1.0, "percent_applicable": 1.0}, "Neutrality": {"sampling_as_desired": "Yes (400/400)", "cond_satisfaction": 1.0, "absolute_satisfaction": 1.0, "percent_applicable": 1.0}, "Condorcet": {"sampling_as_desired": "Yes (400/400)", "cond_satisfaction": 0.55, "absolute_satisfaction": 0.6407185628742516, "percent_applicable": 0.7984031936127745}, "Pareto": {"sampling_as_desired": "Yes (400/400)", "cond_satisfaction": 1.0, "absolute_satisfaction": 1.0, "percent_applicable": 0.04727014890096904}, "Independence": {"sampling_as_desired": "Yes (400/400)", "cond_satisfaction": 0.18, "absolute_satisfaction": 0.53737658674189, "percent_applicable": 0.5641748942172073}}, "neut-anon": null}, "similarity_to_other_rules": {"plain": {"Stable Voting": {"hamming": 0.24823333333333336, "identity_accu": 0.424, "overlap_accu": 0.996, "subset_accu": 0.428, "superset_accu": 0.99}, "Blacks": {"hamming": 0.25036666666666674, "identity_accu": 0.422, "overlap_accu": 0.99, "subset_accu": 0.426, "superset_accu": 0.986}, "Borda": {"hamming": 0.25013333333333343, "identity_accu": 0.424, "overlap_accu": 0.988, "subset_accu": 0.43, "superset_accu": 0.982}, "Weak Nanson": {"hamming": 0.24076666666666674, "identity_accu": 0.44, "overlap_accu": 0.996, "subset_accu": 0.444, "superset_accu": 0.98}, "Copeland": {"hamming": 0.2367333333333334, "identity_accu": 0.44, "overlap_accu": 0.996, "subset_accu": 0.462, "superset_accu": 0.958}}, "neut": {"Stable Voting": {"hamming": 0.24626666666666672, "identity_accu": 0.464, "overlap_accu": 1.0, "subset_accu": 0.464, "superset_accu": 1.0}, "Blacks": {"hamming": 0.24793333333333337, "identity_accu": 0.458, "overlap_accu": 0.998, "subset_accu": 0.458, "superset_accu": 0.998}, "Borda": {"hamming": 0.24536666666666668, "identity_accu": 0.466, "overlap_accu": 0.998, "subset_accu": 0.466, "superset_accu": 0.998}, "Weak Nanson": {"hamming": 0.23553333333333332, "identity_accu": 0.482, "overlap_accu": 1.0, "subset_accu": 0.482, "superset_accu": 1.0}, "Copeland": {"hamming": 0.22996666666666665, "identity_accu": 0.482, "overlap_accu": 1.0, "subset_accu": 0.5, "superset_accu": 0.98}}, "neut-anon": null}}, "12499": {"loss_on_last_batch": {"loss_nowi": 0.0, "loss_alwi": 0, "loss_inad": 0, "loss_reso": 0, "loss_pari": 0, "loss_anon": 0, "loss_neut": 0, "loss_con1": 0.049374401569366455, "loss_con2": 0, "loss_par1": 0.07862211763858795, "loss_par2": 0, "loss_inde": 0}, "admissability": {"plain": {"no_winner_at_all": 0.0, "no_admissible_winner": 0.0, "all_admissible_winner": 0.32, "some_inadmissible_winner": 0.696}, "neut": {"no_winner_at_all": 0.0, "no_admissible_winner": 0.0, "all_admissible_winner": 0.398, "some_inadmissible_winner": 0.734}, "neut-anon": null}, "axiom_satisfaction": {"plain": {"Anonymity": {"sampling_as_desired": "Yes (400/400)", "cond_satisfaction": 1.0, "absolute_satisfaction": 1.0, "percent_applicable": 1.0}, "Neutrality": {"sampling_as_desired": "Yes (400/400)", "cond_satisfaction": 0.2375, "absolute_satisfaction": 0.2375, "percent_applicable": 1.0}, "Condorcet": {"sampling_as_desired": "Yes (400/400)", "cond_satisfaction": 0.575, "absolute_satisfaction": 0.6606786427145709, "percent_applicable": 0.7984031936127745}, "Pareto": {"sampling_as_desired": "Yes (400/400)", "cond_satisfaction": 0.95, "absolute_satisfaction": 0.9976605450929933, "percent_applicable": 0.04678909814013335}, "Independence": {"sampling_as_desired": "Yes (400/400)", "cond_satisfaction": 0.22, "absolute_satisfaction": 0.47297297297297297, "percent_applicable": 0.6756756756756757}}, "neut": {"Anonymity": {"sampling_as_desired": "Yes (400/400)", "cond_satisfaction": 1.0, "absolute_satisfaction": 1.0, "percent_applicable": 1.0}, "Neutrality": {"sampling_as_desired": "Yes (400/400)", "cond_satisfaction": 1.0, "absolute_satisfaction": 1.0, "percent_applicable": 1.0}, "Condorcet": {"sampling_as_desired": "Yes (400/400)", "cond_satisfaction": 0.6475, "absolute_satisfaction": 0.709278350515464, "percent_applicable": 0.8247422680412371}, "Pareto": {"sampling_as_desired": "Yes (400/400)", "cond_satisfaction": 1.0, "absolute_satisfaction": 1.0, "percent_applicable": 0.04503997297601622}, "Independence": {"sampling_as_desired": "Yes (400/400)", "cond_satisfaction": 0.1, "absolute_satisfaction": 0.4805194805194805, "percent_applicable": 0.5772005772005772}}, "neut-anon": null}, "similarity_to_other_rules": {"plain": {"Stable Voting": {"hamming": 0.18180000000000018, "identity_accu": 0.57, "overlap_accu": 0.976, "subset_accu": 0.586, "superset_accu": 0.954}, "Blacks": {"hamming": 0.1857333333333335, "identity_accu": 0.568, "overlap_accu": 0.968, "subset_accu": 0.578, "superset_accu": 0.946}, "Borda": {"hamming": 0.1840333333333335, "identity_accu": 0.57, "overlap_accu": 0.968, "subset_accu": 0.58, "superset_accu": 0.946}, "Weak Nanson": {"hamming": 0.1780000000000001, "identity_accu": 0.568, "overlap_accu": 0.984, "subset_accu": 0.594, "superset_accu": 0.942}, "Copeland": {"hamming": 0.17750000000000013, "identity_accu": 0.564, "overlap_accu": 0.984, "subset_accu": 0.608, "superset_accu": 0.914}}, "neut": {"Stable Voting": {"hamming": 0.1793, "identity_accu": 0.582, "overlap_accu": 1.0, "subset_accu": 0.582, "superset_accu": 1.0}, "Blacks": {"hamming": 0.17963333333333337, "identity_accu": 0.58, "overlap_accu": 1.0, "subset_accu": 0.58, "superset_accu": 1.0}, "Borda": {"hamming": 0.17706666666666668, "identity_accu": 0.588, "overlap_accu": 1.0, "subset_accu": 0.588, "superset_accu": 1.0}, "Weak Nanson": {"hamming": 0.17056666666666673, "identity_accu": 0.606, "overlap_accu": 1.0, "subset_accu": 0.61, "superset_accu": 0.996}, "Copeland": {"hamming": 0.15640000000000007, "identity_accu": 0.622, "overlap_accu": 1.0, "subset_accu": 0.632, "superset_accu": 0.988}}, "neut-anon": null}}, "14999": {"loss_on_last_batch": {"loss_nowi": 0.0, "loss_alwi": 0, "loss_inad": 0, "loss_reso": 0, "loss_pari": 0, "loss_anon": 0, "loss_neut": 0, "loss_con1": 0.04421238973736763, "loss_con2": 0, "loss_par1": 0.08178456127643585, "loss_par2": 0, "loss_inde": 0}, "admissability": {"plain": {"no_winner_at_all": 0.0, "no_admissible_winner": 0.0, "all_admissible_winner": 0.402, "some_inadmissible_winner": 0.606}, "neut": {"no_winner_at_all": 0.0, "no_admissible_winner": 0.0, "all_admissible_winner": 0.424, "some_inadmissible_winner": 0.638}, "neut-anon": null}, "axiom_satisfaction": {"plain": {"Anonymity": {"sampling_as_desired": "Yes (400/400)", "cond_satisfaction": 1.0, "absolute_satisfaction": 1.0, "percent_applicable": 1.0}, "Neutrality": {"sampling_as_desired": "Yes (400/400)", "cond_satisfaction": 0.325, "absolute_satisfaction": 0.325, "percent_applicable": 1.0}, "Condorcet": {"sampling_as_desired": "Yes (400/400)", "cond_satisfaction": 0.4625, "absolute_satisfaction": 0.5784313725490197, "percent_applicable": 0.7843137254901961}, "Pareto": {"sampling_as_desired": "Yes (400/400)", "cond_satisfaction": 0.985, "absolute_satisfaction": 0.9992685602828234, "percent_applicable": 0.04876264781177618}, "Independence": {"sampling_as_desired": "Yes (400/400)", "cond_satisfaction": 0.19, "absolute_satisfaction": 0.4968944099378882, "percent_applicable": 0.6211180124223602}}, "neut": {"Anonymity": {"sampling_as_desired": "Yes (400/400)", "cond_satisfaction": 1.0, "absolute_satisfaction": 1.0, "percent_applicable": 1.0}, "Neutrality": {"sampling_as_desired": "Yes (400/400)", "cond_satisfaction": 1.0, "absolute_satisfaction": 1.0, "percent_applicable": 1.0}, "Condorcet": {"sampling_as_desired": "Yes (400/400)", "cond_satisfaction": 0.445, "absolute_satisfaction": 0.5506072874493927, "percent_applicable": 0.8097165991902834}, "Pareto": {"sampling_as_desired": "Yes (400/400)", "cond_satisfaction": 1.0, "absolute_satisfaction": 1.0, "percent_applicable": 0.04689331770222743}, "Independence": {"sampling_as_desired": "Yes (400/400)", "cond_satisfaction": 0.1725, "absolute_satisfaction": 0.48919753086419754, "percent_applicable": 0.6172839506172839}}, "neut-anon": null}, "similarity_to_other_rules": {"plain": {"Stable Voting": {"hamming": 0.2808, "identity_accu": 0.38, "overlap_accu": 0.998, "subset_accu": 0.384, "superset_accu": 0.992}, "Blacks": {"hamming": 0.2811333333333334, "identity_accu": 0.376, "overlap_accu": 1.0, "subset_accu": 0.382, "superset_accu": 0.992}, "Borda": {"hamming": 0.27856666666666674, "identity_accu": 0.382, "overlap_accu": 1.0, "subset_accu": 0.388, "superset_accu": 0.992}, "Weak Nanson": {"hamming": 0.27286666666666676, "identity_accu": 0.394, "overlap_accu": 0.998, "subset_accu": 0.398, "superset_accu": 0.986}, "Copeland": {"hamming": 0.2673666666666667, "identity_accu": 0.404, "overlap_accu": 0.998, "subset_accu": 0.42, "superset_accu": 0.962}}, "neut": {"Stable Voting": {"hamming": 0.2653666666666667, "identity_accu": 0.396, "overlap_accu": 1.0, "subset_accu": 0.396, "superset_accu": 1.0}, "Blacks": {"hamming": 0.26570000000000005, "identity_accu": 0.394, "overlap_accu": 1.0, "subset_accu": 0.394, "superset_accu": 1.0}, "Borda": {"hamming": 0.26446666666666674, "identity_accu": 0.404, "overlap_accu": 0.998, "subset_accu": 0.404, "superset_accu": 0.998}, "Weak Nanson": {"hamming": 0.2546333333333334, "identity_accu": 0.43, "overlap_accu": 1.0, "subset_accu": 0.43, "superset_accu": 1.0}, "Copeland": {"hamming": 0.2480666666666668, "identity_accu": 0.43, "overlap_accu": 1.0, "subset_accu": 0.45, "superset_accu": 0.978}}, "neut-anon": null}}}, "admissability": {"plain": {"no_winner_at_all": 0.0, "no_admissible_winner": 0.0, "all_admissible_winner": 0.398, "some_inadmissible_winner": 0.606}, "neut": {"no_winner_at_all": 0.0, "no_admissible_winner": 0.0, "all_admissible_winner": 0.43, "some_inadmissible_winner": 0.64}, "neut-anon": null}, "axiom_satisfaction": {"model_plain": {"Anonymity": {"sampling_as_desired": "Yes (400/400)", "cond_satisfaction": 1.0, "absolute_satisfaction": 1.0, "percent_applicable": 1.0}, "Neutrality": {"sampling_as_desired": "Yes (400/400)", "cond_satisfaction": 0.3025, "absolute_satisfaction": 0.3025, "percent_applicable": 1.0}, "Condorcet": {"sampling_as_desired": "Yes (400/400)", "cond_satisfaction": 0.4475, "absolute_satisfaction": 0.5489795918367347, "percent_applicable": 0.8163265306122449}, "Pareto": {"sampling_as_desired": "Yes (400/400)", "cond_satisfaction": 0.9775, "absolute_satisfaction": 0.998825525251207, "percent_applicable": 0.05219887772412893}, "Independence": {"sampling_as_desired": "Yes (400/400)", "cond_satisfaction": 0.175, "absolute_satisfaction": 0.4915254237288136, "percent_applicable": 0.6163328197226502}}, "model_neut": {"Anonymity": {"sampling_as_desired": "Yes (400/400)", "cond_satisfaction": 1.0, "absolute_satisfaction": 1.0, "percent_applicable": 1.0}, "Neutrality": {"sampling_as_desired": "Yes (400/400)", "cond_satisfaction": 1.0, "absolute_satisfaction": 1.0, "percent_applicable": 1.0}, "Condorcet": {"sampling_as_desired": "Yes (400/400)", "cond_satisfaction": 0.4875, "absolute_satisfaction": 0.5781893004115226, "percent_applicable": 0.823045267489712}, "Pareto": {"sampling_as_desired": "Yes (400/400)", "cond_satisfaction": 1.0, "absolute_satisfaction": 1.0, "percent_applicable": 0.04811161895597787}, "Independence": {"sampling_as_desired": "Yes (400/400)", "cond_satisfaction": 0.165, "absolute_satisfaction": 0.5102639296187683, "percent_applicable": 0.5865102639296188}}, "model_neut_anon": null, "Stable Voting": {"Condorcet": {"sampling_as_desired": "Yes (400/400)", "cond_satisfaction": 1.0, "absolute_satisfaction": 1.0, "percent_applicable": 0.7984031936127745}, "Independence": {"sampling_as_desired": "Yes (400/400)", "cond_satisfaction": 0.395, "absolute_satisfaction": 0.5245579567779961, "percent_applicable": 0.7858546168958742}}, "Blacks": {"Condorcet": {"sampling_as_desired": "Yes (400/400)", "cond_satisfaction": 1.0, "absolute_satisfaction": 1.0, "percent_applicable": 0.796812749003984}, "Independence": {"sampling_as_desired": "Yes (400/400)", "cond_satisfaction": 0.345, "absolute_satisfaction": 0.46963562753036436, "percent_applicable": 0.8097165991902834}}, "Borda": {"Condorcet": {"sampling_as_desired": "Yes (400/400)", "cond_satisfaction": 0.935, "absolute_satisfaction": 0.9489194499017681, "percent_applicable": 0.7858546168958742}, "Independence": {"sampling_as_desired": "Yes (400/400)", "cond_satisfaction": 0.36, "absolute_satisfaction": 0.49206349206349204, "percent_applicable": 0.7936507936507936}}, "Weak Nanson": {"Condorcet": {"sampling_as_desired": "Yes (400/400)", "cond_satisfaction": 1.0, "absolute_satisfaction": 1.0, "percent_applicable": 0.7905138339920948}, "Independence": {"sampling_as_desired": "Yes (400/400)", "cond_satisfaction": 0.3875, "absolute_satisfaction": 0.5288461538461539, "percent_applicable": 0.7692307692307693}}, "Copeland": {"Condorcet": {"sampling_as_desired": "Yes (400/400)", "cond_satisfaction": 1.0, "absolute_satisfaction": 1.0, "percent_applicable": 0.8}, "Independence": {"sampling_as_desired": "Yes (400/400)", "cond_satisfaction": 0.3025, "absolute_satisfaction": 0.4507874015748031, "percent_applicable": 0.7874015748031497}}, "Baldwin": {"Condorcet": {"sampling_as_desired": "Yes (400/400)", "cond_satisfaction": 1.0, "absolute_satisfaction": 1.0, "percent_applicable": 0.8064516129032258}, "Independence": {"sampling_as_desired": "Yes (400/400)", "cond_satisfaction": 0.3425, "absolute_satisfaction": 0.5009487666034156, "percent_applicable": 0.7590132827324478}}, "Kemeny-Young": {"Condorcet": {"sampling_as_desired": "Yes (400/400)", "cond_satisfaction": 1.0, "absolute_satisfaction": 1.0, "percent_applicable": 0.8403361344537815}, "Independence": {"sampling_as_desired": "Yes (400/400)", "cond_satisfaction": 0.3575, "absolute_satisfaction": 0.5009708737864078, "percent_applicable": 0.7766990291262136}}}, "rule_comparison": {"plain": {"Stable Voting": {"hamming": 0.2583333333333333, "identity_accu": 0.408, "overlap_accu": 0.996, "subset_accu": 0.416, "superset_accu": 0.986}, "Blacks": {"hamming": 0.25953333333333334, "identity_accu": 0.41, "overlap_accu": 0.996, "subset_accu": 0.418, "superset_accu": 0.984}, "Borda": {"hamming": 0.255, "identity_accu": 0.418, "overlap_accu": 0.996, "subset_accu": 0.426, "superset_accu": 0.982}, "Weak Nanson": {"hamming": 0.2533666666666667, "identity_accu": 0.426, "overlap_accu": 0.998, "subset_accu": 0.438, "superset_accu": 0.986}, "Copeland": {"hamming": 0.24770000000000006, "identity_accu": 0.426, "overlap_accu": 0.998, "subset_accu": 0.452, "superset_accu": 0.968}}, "neut": {"Stable Voting": {"hamming": 0.2541666666666669, "identity_accu": 0.426, "overlap_accu": 1.0, "subset_accu": 0.426, "superset_accu": 1.0}, "Blacks": {"hamming": 0.25436666666666685, "identity_accu": 0.42, "overlap_accu": 1.0, "subset_accu": 0.42, "superset_accu": 1.0}, "Borda": {"hamming": 0.2488333333333335, "identity_accu": 0.436, "overlap_accu": 1.0, "subset_accu": 0.436, "superset_accu": 1.0}, "Weak Nanson": {"hamming": 0.24840000000000012, "identity_accu": 0.454, "overlap_accu": 1.0, "subset_accu": 0.454, "superset_accu": 1.0}, "Copeland": {"hamming": 0.24326666666666683, "identity_accu": 0.45, "overlap_accu": 1.0, "subset_accu": 0.466, "superset_accu": 0.98}}, "neut-anon": null}, "runtime_in_sec": 87947.0024137497}